calibre/__init__.py
calibre/calibration.py
calibre/metrics.py
calibre/utils.py
calibre_ml-0.1.1.dist-info/licenses/LICENSE
calibre_ml-0.1.1.dist-info/METADATA
calibre_ml-0.1.1.dist-info/WHEEL
calibre_ml-0.1.1.dist-info/top_level.txt
calibre_ml-0.1.1.dist-info/RECORD
