Metadata-Version: 2.4
Name: calibre-ml
Version: 0.1.1
Summary: Advanced probability calibration techniques for machine learning models
Author-email: Gaurav Sood <gsood07@gmail.com>
License: MIT
Project-URL: Homepage, https://github.com/soodoku/calibre-ml
Project-URL: Bug Tracker, https://github.com/soodoku/calibre-ml/issues
Project-URL: Documentation, https://github.com/soodoku/calibre-ml#readme
Classifier: Programming Language :: Python :: 3
Classifier: License :: OSI Approved :: MIT License
Classifier: Operating System :: OS Independent
Classifier: Topic :: Scientific/Engineering :: Artificial Intelligence
Classifier: Topic :: Scientific/Engineering :: Mathematics
Classifier: Topic :: Scientific/Engineering :: Information Analysis
Requires-Python: >=3.8
License-File: LICENSE
Requires-Dist: numpy>=1.20.0
Requires-Dist: scipy>=1.7.0
Requires-Dist: scikit-learn>=1.0.0
Requires-Dist: cvxpy>=1.2.0
Requires-Dist: pandas>=1.3.0
Requires-Dist: matplotlib>=3.4.0
Provides-Extra: dev
Requires-Dist: pytest>=6.0.0; extra == "dev"
Requires-Dist: pytest-cov>=2.12.0; extra == "dev"
Requires-Dist: black>=21.5b2; extra == "dev"
Requires-Dist: mypy>=0.812; extra == "dev"
Requires-Dist: isort>=5.9.0; extra == "dev"
Dynamic: license-file
